curls_cli-0.0.2.data/scripts/curls
src/__init__.py
src/commands/__init__.py
src/commands/base.py
src/commands/delete.py
src/commands/describe.py
src/commands/error.py
src/commands/export.py
src/commands/help.py
src/commands/history.py
src/commands/imp.py
src/commands/info.py
src/commands/name.py
src/commands/reset.py
src/commands/result.py
src/commands/use.py
src/commands/api/__init__.py
src/commands/api/add.py
src/commands/api/create.py
src/commands/api/delete.py
src/commands/api/list.py
src/commands/api/remove.py
src/data/__init__.py
src/data/models/__init__.py
src/data/models/api.py
src/data/models/base.py
src/data/models/curl.py
src/data/models/joins.py
src/data/queries/__init__.py
src/data/queries/api.py
src/data/queries/curl.py
src/formatting/__init__.py
src/formatting/text.py
tests/__init__.py
curls_cli-0.0.2.dist-info/METADATA
curls_cli-0.0.2.dist-info/WHEEL
curls_cli-0.0.2.dist-info/top_level.txt
curls_cli-0.0.2.dist-info/RECORD
