Metadata-Version: 2.1
Name: curls-cli
Version: 0.0.2
Summary: A command-line alternative to Postman.
Home-page: http://github.com/ptbrodie/curls
Author: Patrick Brodie
Requires-Dist: certifi ==2024.2.2
Requires-Dist: charset-normalizer ==3.3.2
Requires-Dist: dateparser ==1.2.0
Requires-Dist: idna ==3.6
Requires-Dist: peewee ==3.17.1
Requires-Dist: python-dateutil ==2.8.2
Requires-Dist: pytz ==2024.1
Requires-Dist: regex ==2023.12.25
Requires-Dist: requests ==2.31.0
Requires-Dist: six ==1.16.0
Requires-Dist: termcolor ==2.4.0
Requires-Dist: terminaltables ==3.1.0
Requires-Dist: tzlocal ==5.2
Requires-Dist: urllib3 ==1.26.18
